setup.cfg
setup.py
speech_timer.egg-info/PKG-INFO
speech_timer.egg-info/SOURCES.txt
speech_timer.egg-info/dependency_links.txt
speech_timer.egg-info/requires.txt
speech_timer.egg-info/top_level.txt
timer_mod/__init__.py
timer_mod/functions.py